Metadata-Version: 2.1
Name: odoo-addon-account_invoice_start_end_dates
Version: 19.0.1.0.0.3
Requires-Dist: odoo==19.0.*
Summary: Adds start/end dates on invoice/move lines
Home-page: https://github.com/OCA/account-closing
License: LGPL-3
Author: Akretion,Odoo Community Association (OCA)
Author-email: support@odoo-community.org
Classifier: Programming Language :: Python
Classifier: Framework :: Odoo
Classifier: Framework :: Odoo :: 19.0
Classifier: License :: OSI Approved :: GNU Lesser General Public License v3 (LGPLv3)
